utcp_agent/__init__.py
utcp_agent/utcp_agent.py
utcp_agent-1.0.3.dist-info/licenses/LICENSE
utcp_agent-1.0.3.dist-info/METADATA
utcp_agent-1.0.3.dist-info/WHEEL
utcp_agent-1.0.3.dist-info/top_level.txt
utcp_agent-1.0.3.dist-info/RECORD
