Metadata-Version: 2.4
Name: utcp-agent
Version: 1.0.3
Summary: A ready-to-use agent for UTCP tool calling
Author: UTCP Team
Maintainer: UTCP Team
License-Expression: MPL-2.0
Project-URL: Homepage, https://utcp.io
Project-URL: Source, https://github.com/universal-tool-calling-protocol/utcp-agent
Project-URL: Issues, https://github.com/universal-tool-calling-protocol/utcp-agent/issues
Keywords: ai,agent,utcp,langgraph,langchain,tools
Classifier: Development Status :: 4 - Beta
Classifier: Intended Audience :: Developers
Classifier: Programming Language :: Python :: 3
Classifier: Operating System :: OS Independent
Requires-Python: >=3.9
License-File: LICENSE
Requires-Dist: langgraph>=0.0.40
Requires-Dist: langchain-core>=0.1.0
Requires-Dist: langchain>=0.1.0
Requires-Dist: pydantic>=2.0.0
Requires-Dist: utcp>=1.0.1
Requires-Dist: utcp-http>=1.0.3
Requires-Dist: utcp-mcp>=1.0.1
Requires-Dist: utcp-text>=1.0.1
Requires-Dist: utcp-cli>=1.0.1
Provides-Extra: openai
Requires-Dist: langchain-openai>=0.1.0; extra == "openai"
Provides-Extra: anthropic
Requires-Dist: langchain-anthropic>=0.1.0; extra == "anthropic"
Provides-Extra: community
Requires-Dist: langchain-community>=0.0.20; extra == "community"
Provides-Extra: examples
Requires-Dist: python-dotenv>=1.0.0; extra == "examples"
Requires-Dist: langchain-openai>=0.1.0; extra == "examples"
Requires-Dist: langchain-anthropic>=0.1.0; extra == "examples"
Requires-Dist: langchain-community>=0.0.20; extra == "examples"
Provides-Extra: observability
Requires-Dist: langsmith>=0.1.0; extra == "observability"
Provides-Extra: dev
Requires-Dist: build; extra == "dev"
Requires-Dist: pytest; extra == "dev"
Requires-Dist: pytest-asyncio; extra == "dev"
Requires-Dist: pytest-cov; extra == "dev"
Requires-Dist: coverage; extra == "dev"
Requires-Dist: twine; extra == "dev"
Provides-Extra: llm-all
Requires-Dist: langchain-openai>=0.1.0; extra == "llm-all"
Requires-Dist: langchain-anthropic>=0.1.0; extra == "llm-all"
Requires-Dist: langchain-community>=0.0.20; extra == "llm-all"
Provides-Extra: all
Requires-Dist: langchain-openai>=0.1.0; extra == "all"
Requires-Dist: langchain-anthropic>=0.1.0; extra == "all"
Requires-Dist: langchain-community>=0.0.20; extra == "all"
Requires-Dist: langsmith>=0.1.0; extra == "all"
Dynamic: license-file
